dxutils/__init__.py
dxutils/__main__.py
dxutils/_nbdev.py
dxutils/_version.py
dxutils/alamode.py
dxutils/core.py
dxutils/get_disp_force.py
dxutils/make_gen.py
dxutils/plot.py
dxutils/plotband.py
dxutils/plotdos.py
dxutils/utils.py
prev_ver/__init__.py
prev_ver/__main__.py
prev_ver/_nbdev.py
prev_ver/_version.py
prev_ver/get_disp_force.py
prev_ver/make_gen.py
prev_ver/plotband.py
prev_ver/plotdos.py
prev_ver/utils.py
tests/__init__.py
tests/test_utils.py
dxutils-0.5.13.dist-info/LICENSE
dxutils-0.5.13.dist-info/METADATA
dxutils-0.5.13.dist-info/WHEEL
dxutils-0.5.13.dist-info/entry_points.txt
dxutils-0.5.13.dist-info/top_level.txt
dxutils-0.5.13.dist-info/RECORD
