Metadata-Version: 2.1
Name: dxutils
Version: 0.5.13
Summary: A small toolbox for computational solid state physics
Home-page: https://github.com/jochym/dxutils/tree/nbdev/
Author: Pawel T. Jochym
Author-email: pawel.jochym@ifj.edu.pl
License: GNU General Public License v3
Keywords: physics utils
Platform: UNKNOWN
Classifier: Development Status :: 4 - Beta
Classifier: Intended Audience :: Developers
Classifier: Natural Language :: English
Classifier: Programming Language :: Python :: 3.6
Classifier: Programming Language :: Python :: 3.7
Classifier: Programming Language :: Python :: 3.8
Classifier: License :: OSI Approved :: GNU General Public License v3 (GPLv3)
Requires-Python: >=3.6
License-File: LICENSE
Requires-Dist: pip
Requires-Dist: packaging
Requires-Dist: numpy
Requires-Dist: ase
Requires-Dist: spglib
Requires-Dist: click
Requires-Dist: matplotlib
Provides-Extra: dev
